<!-- removed DTD reference - otherwise jaxb tries to connect to the referenced oasis web site -->

<catalog xmlns="urn:oasis:names:tc:entity:xmlns:xml:catalog" prefer="public">
	<uri name="org.kalypso.model.wspmbreakline" uri="schemata/breakline.xsd" />
	<uri name="org.kalypso.model.wspm.nawspm" uri="schemata/couplingNaWspm.xsd" />
	<uri name="org.kalypso.model.wspmboundary" uri="schemata/floodBoundary.xsd" />
	<uri name="org.kalypso.model.wspmprofile" uri="schemata/profile.xsd" />
	<uri name="org.kalypso.model.wspmprofile.assignment" uri="schemata/profilePointAssignment.xsd" />
	<uri name="org.kalypso.model.wspmrunoff" uri="schemata/runOff.xsd" />
	<uri name="org.kalypso.model.wspm" uri="schemata/wspm.xsd" />
	<uri name="org.kalypso.model.wspmcommon" uri="schemata/wspmCommons.xsd" />
	<uri name="org.kalypso.model.wspmproj" uri="schemata/wspmProject.xsd" />
    <uri name="org.kalypso.model.wspm.classifications" uri="schemata/wspmClassifications.xsd" />
</catalog>
